MANIFEST.in
README.rst
setup.py
bin/ccypher
ccypher/__init__.py
ccypher/ccfunctions.py
ccypher/ccypher.py
ccypher.egg-info/PKG-INFO
ccypher.egg-info/SOURCES.txt
ccypher.egg-info/dependency_links.txt
ccypher.egg-info/not-zip-safe
ccypher.egg-info/requires.txt
ccypher.egg-info/top_level.txt